stancmd/__init__.py
stancmd/main.py
stancmd/stan/__init__.py
stancmd/utils/__init__.py
stancmd-0.2.11.dist-info/METADATA
stancmd-0.2.11.dist-info/WHEEL
stancmd-0.2.11.dist-info/entry_points.txt
stancmd-0.2.11.dist-info/top_level.txt
stancmd-0.2.11.dist-info/RECORD
