Metadata-Version: 2.1
Name: stancmd
Version: 0.2.11
Summary: A useless command line patience tester
Home-page: https://gitlab.com/quentin-dev/stan
Author: Quentin Barbarat
Author-email: q.barbarat@gmail.com
License: UNKNOWN
Platform: UNKNOWN
Classifier: Programming Language :: Python :: 3
Classifier: Operating System :: OS Independent
Requires-Python: >=3.7
